{
  "$schema": "https://biomejs.dev/schemas/2.1.4/schema.json",
  "formatter": {
    "enabled": true,
    "formatWithErrors": false,
    "indentStyle": "space",
    "indentWidth": 2,
    "lineEnding": "lf",
    "lineWidth": 80
  },
  "javascript": {
    "formatter": {
      "arrowParentheses": "always",
      "bracketSameLine": false,
      "bracketSpacing": true,
      "jsxQuoteStyle": "double",
      "quoteProperties": "asNeeded",
      "quoteStyle": "double",
      "semicolons": "always",
      "trailingCommas": "es5"
    }
  },
  "linter": {
    "enabled": true,
    "rules": {
      "recommended": true,
      "correctness": {
        "noUnusedVariables": "error",
        "noUnusedImports": "error",
        "noUnusedFunctionParameters": "error"
      },
      "complexity": {
        "noUselessFragments": "warn"
      },
      "a11y": {
        "noStaticElementInteractions": "warn",
        "useKeyWithClickEvents": "warn",
        "useFocusableInteractive": "warn",
        "useSemanticElements": "warn",
        "noRedundantRoles": "warn",
        "useAriaPropsForRole": "warn"
      },
      "security": {
        "noDangerouslySetInnerHtml": "warn"
      },
      "style": {
        "useNamingConvention": "off",
        "noNonNullAssertion": "warn"
      },
      "suspicious": {
        "noExplicitAny": "warn",
        "noArrayIndexKey": "warn",
        "noConfusingVoidType": "warn",
        "noDocumentCookie": "warn"
      }
    }
  },
  "overrides": [
    {
      "includes": ["src/components/ui/**"],
      "linter": {
        "rules": {
          "a11y": {
            "noStaticElementInteractions": "off",
            "useKeyWithClickEvents": "off",
            "useFocusableInteractive": "off",
            "useSemanticElements": "off",
            "noRedundantRoles": "off",
            "useAriaPropsForRole": "off"
          },
          "security": {
            "noDangerouslySetInnerHtml": "off"
          },
          "suspicious": {
            "noDocumentCookie": "off"
          },
          "correctness": {
            "noUnusedFunctionParameters": "off"
          }
        }
      }
    }
  ],
  "files": {
    "includes": [
      "**/*.js",
      "**/*.jsx",
      "**/*.ts",
      "**/*.tsx",
      "**/*.json",
      "**/*.jsonc"
    ]
  }
}
